{
  "word": "counterparts",
  "createdAt": "2026-04-29",
  "reviews": [],
  "definitions": [],
  "examples": [
    {
      "text": "The result? Cantonese versions\nwere consistently more tone sensitive than the Mandarin counterparts,\nwith 77% of the lyrics matching the melody, while the Mandarin\nversions only matched 38%. That being said, the songs used for\nthese tests are all over",
      "explanation": "",
      "focusWords": [
        "counterparts"
      ],
      "source": {
        "text": "Chinese Music - It's Not Dead, It's Misunderstood...",
        "url": ""
      },
      "youtube": {
        "url": "https://www.youtube.com/watch?v=1qiv68LKZjo",
        "timestamp": 648
      }
    }
  ]
}