{
  "word": "lurk",
  "createdAt": "2026-03-27",
  "reviews": [
    {
      "date": "2026-04-12",
      "score": 1
    },
    {
      "date": "2026-04-13",
      "score": 2
    },
    {
      "date": "2026-04-17",
      "score": 1
    }
  ],
  "definitions": [
    "v. 潜伏；潜藏"
  ],
  "examples": [
    {
      "text": "We are scared by the dangers that lurk in the dark, imagined and real ones.",
      "explanation": "此处 'lurk' 作动词，意为‘潜伏’或‘潜藏’，常指危险或负面事物隐藏在暗处。",
      "focusWords": [
        "lurk"
      ],
      "source": {
        "text": "Tired of Doomscrolling?",
        "url": ""
      },
      "youtube": {
        "url": "https://www.youtube.com/watch?v=c1nYtX-NUsc",
        "timestamp": 311
      }
    }
  ]
}