{
  "word": "cynical",
  "createdAt": "2026-04-12",
  "reviews": [],
  "definitions": [
    "略带讽刺地"
  ],
  "examples": [
    {
      "text": "A bit cynically, Bass describes colleagues who never published because they waited so long they became ill or died.",
      "explanation": "巴斯略带讽刺地描述了那些因等待过久而患病或去世、从未发表过论文的同事。",
      "focusWords": [
        "cynically"
      ],
      "source": {
        "text": "CET6 2023 12 2 匹配",
        "url": ""
      }
    }
  ],
  "mergedFrom": [
    "cynically"
  ]
}