{
  "word": "wedge",
  "createdAt": "2026-04-11",
  "reviews": [
    {
      "date": "2026-04-17",
      "score": 2
    }
  ],
  "definitions": [
    "v. 楔入；嵌入（在此语境下指被紧紧卡在泥沙中）"
  ],
  "examples": [
    {
      "text": "Yet some of Cape Canaveral’s most legendary attractions lie unseen, wedged under the sea’s surface in mud and sand, for this part of the world has a reputation as a deadly ship trap.",
      "explanation": "",
      "focusWords": [
        "wedge"
      ],
      "source": {
        "text": "CET6 23 12 2 匹配",
        "url": ""
      },
      "focusPositions": [
        13
      ]
    }
  ],
  "mergedFrom": [
    "wedged"
  ]
}