{
  "word": "glee",
  "createdAt": "2026-06-12",
  "reviews": [],
  "definitions": [],
  "examples": [
    {
      "text": "landing in a far-off region where five pink pillars seemed to mark the edge of the Heavens. Cackling with glee, Sun Wukong proudly marked his territory. Returning to the Buddha, he demanded his new title— but he was distracted by a familiar odor.",
      "explanation": "",
      "focusWords": [
        "glee"
      ],
      "source": {
        "text": "The tale of the Monkey King and the Buddha - Ji Hao",
        "url": "https://www.youtube.com/watch?v=A-oxDZ3AO74"
      },
      "youtube": {
        "url": "https://www.youtube.com/watch?v=A-oxDZ3AO74",
        "timestamp": 80
      }
    }
  ]
}